zkie/__init__.py
zkie-0.1.4.dist-info/DESCRIPTION.rst
zkie-0.1.4.dist-info/METADATA
zkie-0.1.4.dist-info/RECORD
zkie-0.1.4.dist-info/WHEEL
zkie-0.1.4.dist-info/entry_points.txt
zkie-0.1.4.dist-info/metadata.json
zkie-0.1.4.dist-info/top_level.txt
