Metadata-Version: 2.0
Name: zkie
Version: 0.1.4
Summary: zookeeper commandline, like httpie but for zookeeper
Home-page: UNKNOWN
Author: Pierre Tardy
Author-email: tardyp@gmail.com
License: MIT
Platform: UNKNOWN
Requires-Dist: argh
Requires-Dist: future
Requires-Dist: kazoo
Provides-Extra: ui
Requires-Dist: hexdump; extra == 'ui'
Requires-Dist: pygments; extra == 'ui'
